{
  "title": "DeftEval - Extracting Definitions from Free Text",
  "description": "Detect whether a sentence contains a definition and extract term, definition, qualifier, and alias spans from textbook and legal text, based on SemEval-2020 Task 6 (Spala et al.).",
  "version": "1.0.0",
  "author": {
    "name": "Spala et al.",
    "email": "jurgens@umich.edu",
    "github": "SemEval",
    "affiliation": "Adobe Research"
  },
  "createdAt": "2025-01-16",
  "updatedAt": "2025-01-16",
  "annotationTypes": ["span", "radio"],
  "domain": ["NLP", "SemEval"],
  "useCase": ["Definition Extraction", "Information Extraction", "Terminology"],
  "complexity": "intermediate",
  "tags": ["semeval", "semeval-2020", "shared-task", "definition-extraction", "terminology", "information-extraction"],
  "featured": false,
  "paperReference": "Spala et al., SemEval 2020",
  "paperUrl": "https://aclanthology.org/2020.semeval-1.41/",
  "datasetUrl": "https://github.com/adobe-research/deft_corpus",
  "citation": "@inproceedings{spala-etal-2020-semeval,\n    title = \"{S}em{E}val-2020 {T}ask 6: {D}efinition {E}xtraction from {F}ree {T}ext with the {DEFT} {C}orpus\",\n    author = \"Spala, Sasha  and Miller, Nicholas A.  and Yang, Yiming  and Dernoncourt, Franck  and Dockhorn, Carl\",\n    booktitle = \"Proceedings of the Fourteenth Workshop on Semantic Evaluation\",\n    year = \"2020\",\n    publisher = \"Association for Computational Linguistics\",\n    url = \"https://aclanthology.org/2020.semeval-1.41\"\n}"
}
