{
  "title": "FLARE - Financial Named Entity Recognition",
  "description": "Named entity recognition and document classification for financial texts, based on the FLARE benchmark (Xie et al., arXiv 2024). Annotators identify financial entities such as companies, currencies, stock tickers, and amounts, and classify document types.",
  "version": "1.0.0",
  "author": {
    "name": "Xie et al.",
    "email": "",
    "github": "The-FinAI",
    "affiliation": "The FinAI"
  },
  "createdAt": "2025-01-16",
  "updatedAt": "2025-01-16",
  "annotationTypes": [
    "span",
    "radio"
  ],
  "domain": [
    "NLP",
    "Finance"
  ],
  "useCase": [
    "Named Entity Recognition",
    "Financial NLP",
    "Document Classification"
  ],
  "complexity": "intermediate",
  "tags": [
    "ner",
    "finance",
    "entities",
    "flare",
    "financial-text",
    "document-classification"
  ],
  "featured": false,
  "paperReference": "Xie et al., arXiv 2024",
  "paperUrl": "https://arxiv.org/abs/2311.00640",
  "datasetUrl": "https://huggingface.co/TheFinAI",
  "citation": "@article{xie2024finben,\n    title = \"The FinBen: An Holistic Financial Benchmark for Large Language Models\",\n    author = \"Xie, Qianqian and Han, Weiguang and Chen, Zhengyu and Xia, Ruoyu and Zhang, Xiao and He, Yueru and Xiao, Mengxi and Li, Dong and Dai, Yongfu and Feng, Duanyu and others\",\n    journal = \"arXiv preprint arXiv:2311.00640\",\n    year = \"2024\",\n    url = \"https://arxiv.org/abs/2311.00640\"\n}"
}
